{
  "id": "a4247b11-890b-45df-bf42-350a7a3af9be",
  "queryName": "Security Scheme Using HTTP Digest",
  "severity": "LOW",
  "category": "Access Control",
  "descriptionText": "Security Scheme HTTP should not be using digest authentication",
  "descriptionUrl": "https://docs.datadoghq.com/security/code_security/iac_security/iac_security_rules/openAPI/3.0/security_scheme_using_http_digest",
  "platform": "OpenAPI",
  "descriptionID": "2e962b5c",
  "cwe": "",
  "oldSeverity": "MEDIUM",
  "providerUrl": "https://swagger.io/specification/#security-scheme-object"
}