{
  "id": "5572cc5e-1e4c-4113-92a6-7a8a3bd25e6d",
  "queryName": "Privilege escalation allowed",
  "severity": "HIGH",
  "category": "Insecure Configurations",
  "descriptionText": "Containers should not run with `allowPrivilegeEscalation` to prevent them from gaining more privileges than their parent process.",
  "descriptionUrl": "https://docs.datadoghq.com/security/code_security/iac_security/iac_rules/k8s/privilege_escalation_allowed",
  "platform": "Kubernetes",
  "descriptionID": "525fccf4",
  "cwe": "",
  "providerUrl": "https://kubernetes.io/docs/tasks/configure-pod-container/security-context/"
}