{
  "id": "2da46be4-4317-4650-9285-56d7103c4f93",
  "queryName": "Global Security Using Password Flow",
  "severity": "MEDIUM",
  "category": "Access Control",
  "descriptionText": "Security should not use 'password' Flow in OAuth2 authentication",
  "descriptionUrl": "https://docs.datadoghq.com/security/code_security/iac_security/iac_rules/openAPI/2.0/global_security_using_password_flow",
  "platform": "OpenAPI",
  "descriptionID": "14a00e4a",
  "cwe": "",
  "providerUrl": "https://swagger.io/specification/v2/#securityRequirementObject"
}